pokemon_images/__init__.py
pokemon_images/__main__.py
pokemon_images/tests.py
pokemon_images-1.2.2.dist-info/METADATA
pokemon_images-1.2.2.dist-info/WHEEL
pokemon_images-1.2.2.dist-info/licenses/LICENSES/CC-BY-4.0.txt
pokemon_images-1.2.2.dist-info/licenses/LICENSES/CC0-1.0.txt
pokemon_images-1.2.2.dist-info/licenses/LICENSES/LicenseRef-MIT-GitHubModified.txt
pokemon_images-1.2.2.dist-info/licenses/LICENSES/MIT.txt
pokemon_images-1.2.2.dist-info/RECORD
