Metadata-Version: 2.4
Name: pokemon-images
Version: 1.2.2
Summary: Randomly get images of Pokémon from the official Pokémon website
License: MIT
License-File: LICENSES/CC-BY-4.0.txt
License-File: LICENSES/CC0-1.0.txt
License-File: LICENSES/LicenseRef-MIT-GitHubModified.txt
License-File: LICENSES/MIT.txt
Author: Tomodachi94
Requires-Python: >=3.8,<4.0
Classifier: License :: OSI Approved :: MIT License
Classifier: Programming Language :: Python :: 3
Classifier: Programming Language :: Python :: 3.8
Classifier: Programming Language :: Python :: 3.9
Classifier: Programming Language :: Python :: 3.10
Classifier: Programming Language :: Python :: 3.11
Classifier: Programming Language :: Python :: 3.12
Classifier: Programming Language :: Python :: 3.13
Classifier: Programming Language :: Python :: 3.14
Classifier: Topic :: Internet :: WWW/HTTP
Classifier: Topic :: Multimedia
Classifier: Topic :: Utilities
Classifier: Typing :: Typed
Project-URL: Bug Tracker, https://github.com/tomodachi94/pokemon-images.py/issues
Project-URL: Discord, https://discord.gg/Xs3VKNJrMb
Project-URL: Homepage, https://github.com/tomodachi94/pokemon-images.py
Project-URL: Source, https://github.com/tomodachi94/pokemon-images.py
